{
 "slug": "paypay-bank",
 "name": "PayPay銀行",
 "industry": "銀行・証券・保険",
 "soft": {
  "tenkin_do": {
   "value": 2,
   "estimated": true,
   "confidence": "medium",
   "evidence": null
  },
  "kaigai_do": {
   "value": 2,
   "estimated": true,
   "confidence": "medium",
   "evidence": null
  },
  "stability": {
   "value": 4,
   "estimated": true,
   "confidence": "medium",
   "evidence": null
  },
  "growth": {
   "value": 4,
   "estimated": true,
   "confidence": "medium",
   "evidence": null
  },
  "remote_flex": {
   "value": 4,
   "estimated": true,
   "confidence": "medium",
   "evidence": null
  },
  "young_discretion": {
   "value": 4,
   "estimated": true,
   "confidence": "medium",
   "evidence": null
  },
  "bunri": {
   "value": "文理両方",
   "estimated": true,
   "confidence": "medium",
   "evidence": null
  },
  "job_tags": {
   "value": [
    "金融・専門職",
    "企画・マーケティング",
    "デジタル企画",
    "営業"
   ],
   "estimated": true,
   "confidence": "medium",
   "evidence": null
  }
 },
 "facts": {
  "avg_salary": 10649000,
  "starting_salary": {
   "value": 259200,
   "unit": "円/月",
   "evidence": {
    "source_url": "https://syukatsu-kaigi.jp/companies/101234/post_items/2/word_mouths",
    "quote": "**初任給**: 259,200円～290,300円（配属地域の物価による、営業手当19,800円含む） [出典](https://syukatsu-kaigi.jp/companies/101234/post_items/2/word_mouths)"
   },
   "as_of": "",
   "confidence": "high",
   "estimated": false
  },
  "industry": {
   "value": "銀行・証券・保険",
   "estimated": false
  },
  "avg_salary_as_of": "2026年3月期",
  "avg_salary_source": "EDINET:S100YH1E"
 },
 "trend_note": "ネット銀行・PayPay連携で急成長。本社東京のみ、国内完結型。リモート・若手抜擢が高い傾向。成長性重視層向け。",
 "disclaimer": "公式公開情報と業界傾向に基づく参考提案です。",
 "lint": {
  "errors": [],
  "notes": [
   "avg_salary: 有報grade出典なし→null(定性提案)"
  ]
 }
}